Workbook

Sheet Assumptions
A1: PRICING ASSUMPTIONS
A3: Tier | B3: Price | C3: Unit
A4: Day Pass | B4: 2 | C4: per day
A5: Monthly Subscription | B5: 20 | C5: per month
A6: Annual Subscription | B6: 120 | C6: per year
A8: LLM & INFRASTRUCTURE COSTS
A10: Item | B10: Value | C10: Unit
A11: LLM Cost per Chat | B11: 0.003 | C11: USD
A12: Avg Chats per Day Pass | B12: 20 | C12: chats
A13: Avg Chats per Subscriber/Month | B13: 60 | C13: chats
A14: Infrastructure Cost/Month (Base) | B14: 500 | C14: USD
A15: Infrastructure Cost per 10k Users | B15: 200 | C15: USD
A16: Payment Processing Fee | B16: 0.03 | C16: % of revenue
A18: HUMAN & OPERATIONAL COSTS
A20: Role | B20: Monthly Cost (USD) | C20: Needed From (Users) | D20: Notes
A21: Customer Support (Part-time) | B21: 1500 | C21: 5000 | D21: Handle tickets, basic queries
A22: Customer Support (Full-time) | B22: 4000 | C22: 20000 | D22: Dedicated support staff
A23: Content/Marketing (Part-time) | B23: 2000 | C23: 10000 | D23: SEO, blog posts, social
A24: Content/Marketing (Full-time) | B24: 5000 | C24: 30000 | D24: Full marketing ops
A25: Developer (Part-time/Contract) | B25: 3000 | C25: 10000 | D25: Bug fixes, small features
A26: Developer (Full-time) | B26: 8000 | C26: 40000 | D26: Full-time dev work
A27: Accounting/Admin (Part-time) | B27: 500 | C27: 5000 | D27: Invoices, bookkeeping
A28: Legal/Compliance (Retainer) | B28: 500 | C28: 20000 | D28: TOS, privacy, disputes
A31: CONVERSION ASSUMPTIONS
A33: Metric | B33: Value
A34: Monthly Sub Conversion % | B34: 0.015
A35: Annual Sub Conversion % | B35: 0.035
A36: Day Pass Purchase % (of users/month) | B36: 0.1
A38: MARKET SIZE (SINGAPORE)
A40: Segment | B40: Annual Volume | C40: Capture Rate | D40: Captured Users
A41: Car Buyers | B41: 200000 | C41: 0.25 | D41: =B41*C41
A42: Insurance Buyers | B42: 1000000 | C42: 0.05 | D42: =B42*C42
A43: BTO Applicants | B43: 100000 | C43: 0.15 | D43: =B43*C43
A44: General Seasonal | B44: 500000 | C44: 0.1 | D44: =B44*C44
A45: TOTAL DAY PASS USERS | B45: =SUM(B41:B44) | D45: =SUM(D41:D44)

Sheet Yearly Projection
A1: YEAR BY YEAR PROJECTION
A3: Metric | B3: Year 1 | C3: Year 2 | D3: Year 3 | E3: Year 4 | F3: Year 5
A4: Market Penetration % | B4: 0.05 | C4: 0.15 | D4: 0.35 | E4: 0.65 | F4: 1
A5: Registered User Base | B5: 2000 | C5: 8000 | D5: 20000 | E5: 40000 | F5: 60000
A7: DAY PASS USERS
A8: Car Buyers | B8: =Assumptions!$D$41*B$4 | C8: =Assumptions!$D$41*C$4 | D8: =Assumptions!$D$41*D$4 | E8: =Assumptions!$D$41*E$4 | F8: =Assumptions!$D$41*F$4
A9: Insurance Buyers | B9: =Assumptions!$D$42*B$4 | C9: =Assumptions!$D$42*C$4 | D9: =Assumptions!$D$42*D$4 | E9: =Assumptions!$D$42*E$4 | F9: =Assumptions!$D$42*F$4
A10: BTO Applicants | B10: =Assumptions!$D$43*B$4 | C10: =Assumptions!$D$43*C$4 | D10: =Assumptions!$D$43*D$4 | E10: =Assumptions!$D$43*E$4 | F10: =Assumptions!$D$43*F$4
A11: General Seasonal | B11: =Assumptions!$D$44*B$4 | C11: =Assumptions!$D$44*C$4 | D11: =Assumptions!$D$44*D$4 | E11: =Assumptions!$D$44*E$4 | F11: =Assumptions!$D$44*F$4
A12: Total Day Pass Users | B12: =SUM(B8:B11) | C12: =SUM(C8:C11) | D12: =SUM(D8:D11) | E12: =SUM(E8:E11) | F12: =SUM(F8:F11)
A14: SUBSCRIBERS
A15: Monthly Subscribers | B15: =B5*Assumptions!$B$34 | C15: =C5*Assumptions!$B$34 | D15: =D5*Assumptions!$B$34 | E15: =E5*Assumptions!$B$34 | F15: =F5*Assumptions!$B$34
A16: Annual Subscribers | B16: =B5*Assumptions!$B$35 | C16: =C5*Assumptions!$B$35 | D16: =D5*Assumptions!$B$35 | E16: =E5*Assumptions!$B$35 | F16: =F5*Assumptions!$B$35
A17: Total Subscribers | B17: =B15+B16 | C17: =C15+C16 | D17: =D15+D16 | E17: =E15+E16 | F17: =F15+F16
A19: REVENUE
A20: Day Pass Revenue | B20: =B12*Assumptions!$B$4 | C20: =C12*Assumptions!$B$4 | D20: =D12*Assumptions!$B$4 | E20: =E12*Assumptions!$B$4 | F20: =F12*Assumptions!$B$4
A21: Monthly Sub Revenue | B21: =B15*Assumptions!$B$5*12 | C21: =C15*Assumptions!$B$5*12 | D21: =D15*Assumptions!$B$5*12 | E21: =E15*Assumptions!$B$5*12 | F21: =F15*Assumptions!$B$5*12
A22: Annual Sub Revenue | B22: =B16*Assumptions!$B$6 | C22: =C16*Assumptions!$B$6 | D22: =D16*Assumptions!$B$6 | E22: =E16*Assumptions!$B$6 | F22: =F16*Assumptions!$B$6
A23: TOTAL REVENUE | B23: =SUM(B20:B22) | C23: =SUM(C20:C22) | D23: =SUM(D20:D22) | E23: =SUM(E20:E22) | F23: =SUM(F20:F22)
A25: COSTS
A26: LLM Cost (Day Pass) | B26: =B12*Assumptions!$B$12*Assumptions!$B$11 | C26: =C12*Assumptions!$B$12*Assumptions!$B$11 | D26: =D12*Assumptions!$B$12*Assumptions!$B$11 | E26: =E12*Assumptions!$B$12*Assumptions!$B$11 | F26: =F12*Assumptions!$B$12*Assumptions!$B$11
A27: LLM Cost (Subscribers) | B27: =B17*Assumptions!$B$13*12*Assumptions!$B$11 | C27: =C17*Assumptions!$B$13*12*Assumptions!$B$11 | D27: =D17*Assumptions!$B$13*12*Assumptions!$B$11 | E27: =E17*Assumptions!$B$13*12*Assumptions!$B$11 | F27: =F17*Assumptions!$B$13*12*Assumptions!$B$11
A28: Infrastructure Cost | B28: =(Assumptions!$B$14*12)+(B5/10000*Assumptions!$B$15*12) | C28: =(Assumptions!$B$14*12)+(C5/10000*Assumptions!$B$15*12) | D28: =(Assumptions!$B$14*12)+(D5/10000*Assumptions!$B$15*12) | E28: =(Assumptions!$B$14*12)+(E5/10000*Assumptions!$B$15*12) | F28: =(Assumptions!$B$14*12)+(F5/10000*Assumptions!$B$15*12)
A29: Payment Processing (3%) | B29: =B23*Assumptions!$B$16 | C29: =C23*Assumptions!$B$16 | D29: =D23*Assumptions!$B$16 | E29: =E23*Assumptions!$B$16 | F29: =F23*Assumptions!$B$16
A30: Support (Part-time) | B30: =IF(B5>=Assumptions!$C$21,Assumptions!$B$21*12,IF(B5>=Assumptions!$C$21,Assumptions!$B$21*12,0)) | C30: =IF(C5>=Assumptions!$C$21,Assumptions!$B$21*12,IF(C5>=Assumptions!$C$21,Assumptions!$B$21*12,0)) | D30: =IF(D5>=Assumptions!$C$21,Assumptions!$B$21*12,IF(D5>=Assumptions!$C$21,Assumptions!$B$21*12,0)) | E30: =IF(E5>=Assumptions!$C$21,Assumptions!$B$21*12,IF(E5>=Assumptions!$C$21,Assumptions!$B$21*12,0)) | F30: =IF(F5>=Assumptions!$C$21,Assumptions!$B$21*12,IF(F5>=Assumptions!$C$21,Assumptions!$B$21*12,0))
A31: Marketing (Part-time) | B31: =IF(B5>=Assumptions!$C$22,Assumptions!$B$22*12,0) | C31: =IF(C5>=Assumptions!$C$22,Assumptions!$B$22*12,0) | D31: =IF(D5>=Assumptions!$C$22,Assumptions!$B$22*12,0) | E31: =IF(E5>=Assumptions!$C$22,Assumptions!$B$22*12,0) | F31: =IF(F5>=Assumptions!$C$22,Assumptions!$B$22*12,0)
A32: Developer (Part-time) | B32: =IF(B5>=Assumptions!$C$24,Assumptions!$B$24*12,0) | C32: =IF(C5>=Assumptions!$C$24,Assumptions!$B$24*12,0) | D32: =IF(D5>=Assumptions!$C$24,Assumptions!$B$24*12,0) | E32: =IF(E5>=Assumptions!$C$24,Assumptions!$B$24*12,0) | F32: =IF(F5>=Assumptions!$C$24,Assumptions!$B$24*12,0)
A33: Admin/Accounting | B33: =IF(B5>=Assumptions!$C$27,Assumptions!$B$27*12,0) | C33: =IF(C5>=Assumptions!$C$27,Assumptions!$B$27*12,0) | D33: =IF(D5>=Assumptions!$C$27,Assumptions!$B$27*12,0) | E33: =IF(E5>=Assumptions!$C$27,Assumptions!$B$27*12,0) | F33: =IF(F5>=Assumptions!$C$27,Assumptions!$B$27*12,0)
A34: TOTAL COSTS | B34: =SUM(B26:B33) | C34: =SUM(C26:C33) | D34: =SUM(D26:D33) | E34: =SUM(E26:E33) | F34: =SUM(F26:F33)
A36: NET PROFIT | B36: =B23-B34 | C36: =C23-C34 | D36: =D23-D34 | E36: =E23-E34 | F36: =F23-F34
A37: Profit Margin % | B37: =IF(B23>0,B36/B23,0) | C37: =IF(C23>0,C36/C23,0) | D37: =IF(D23>0,D36/D23,0) | E37: =IF(E23>0,E36/E23,0) | F37: =IF(F23>0,F36/F23,0)

Sheet Human Scaling
A1: HUMAN COST SCALING BY USER BASE
A3: This sheet shows when you need to hire based on user thresholds
A5: Users | B5: Support | C5: Marketing | D5: Dev | E5: Admin | F5: Legal | G5: Total Human Cost/Year
A6: 1000 | B6: =IF(A6>=Assumptions!$C$21,Assumptions!$B$21,IF(A6>=Assumptions!$C$21,Assumptions!$B$21,0))*12 | C6: =IF(A6>=Assumptions!$C$22,Assumptions!$B$22,0)*12 | D6: =IF(A6>=Assumptions!$C$24,Assumptions!$B$24,0)*12 | E6: =IF(A6>=Assumptions!$C$27,Assumptions!$B$27,0)*12 | F6: =IF(A6>=Assumptions!$C$28,Assumptions!$B$28,0)*12 | G6: =SUM(B6:F6)
A7: 5000 | B7: =IF(A7>=Assumptions!$C$21,Assumptions!$B$21,IF(A7>=Assumptions!$C$21,Assumptions!$B$21,0))*12 | C7: =IF(A7>=Assumptions!$C$22,Assumptions!$B$22,0)*12 | D7: =IF(A7>=Assumptions!$C$24,Assumptions!$B$24,0)*12 | E7: =IF(A7>=Assumptions!$C$27,Assumptions!$B$27,0)*12 | F7: =IF(A7>=Assumptions!$C$28,Assumptions!$B$28,0)*12 | G7: =SUM(B7:F7)
A8: 10000 | B8: =IF(A8>=Assumptions!$C$21,Assumptions!$B$21,IF(A8>=Assumptions!$C$21,Assumptions!$B$21,0))*12 | C8: =IF(A8>=Assumptions!$C$22,Assumptions!$B$22,0)*12 | D8: =IF(A8>=Assumptions!$C$24,Assumptions!$B$24,0)*12 | E8: =IF(A8>=Assumptions!$C$27,Assumptions!$B$27,0)*12 | F8: =IF(A8>=Assumptions!$C$28,Assumptions!$B$28,0)*12 | G8: =SUM(B8:F8)
A9: 20000 | B9: =IF(A9>=Assumptions!$C$21,Assumptions!$B$21,IF(A9>=Assumptions!$C$21,Assumptions!$B$21,0))*12 | C9: =IF(A9>=Assumptions!$C$22,Assumptions!$B$22,0)*12 | D9: =IF(A9>=Assumptions!$C$24,Assumptions!$B$24,0)*12 | E9: =IF(A9>=Assumptions!$C$27,Assumptions!$B$27,0)*12 | F9: =IF(A9>=Assumptions!$C$28,Assumptions!$B$28,0)*12 | G9: =SUM(B9:F9)
A10: 40000 | B10: =IF(A10>=Assumptions!$C$21,Assumptions!$B$21,IF(A10>=Assumptions!$C$21,Assumptions!$B$21,0))*12 | C10: =IF(A10>=Assumptions!$C$22,Assumptions!$B$22,0)*12 | D10: =IF(A10>=Assumptions!$C$24,Assumptions!$B$24,0)*12 | E10: =IF(A10>=Assumptions!$C$27,Assumptions!$B$27,0)*12 | F10: =IF(A10>=Assumptions!$C$28,Assumptions!$B$28,0)*12 | G10: =SUM(B10:F10)
A11: 60000 | B11: =IF(A11>=Assumptions!$C$21,Assumptions!$B$21,IF(A11>=Assumptions!$C$21,Assumptions!$B$21,0))*12 | C11: =IF(A11>=Assumptions!$C$22,Assumptions!$B$22,0)*12 | D11: =IF(A11>=Assumptions!$C$24,Assumptions!$B$24,0)*12 | E11: =IF(A11>=Assumptions!$C$27,Assumptions!$B$27,0)*12 | F11: =IF(A11>=Assumptions!$C$28,Assumptions!$B$28,0)*12 | G11: =SUM(B11:F11)

Sheet Seasonality
A1: MONTHLY SEASONALITY (MATURE YEAR)
A3: Month | B3: Events | C3: Traffic Multiplier | D3: Day Passes | E3: Revenue | G3: Base Monthly (Yr 5)
A4: Jan | B4: New Year + 2x COE | C4: 1.15 | D4: =$G$4*C4 | E4: =D4*Assumptions!$B$4 | G4: ='Yearly Projection'!F12/12
A5: Feb | B5: CNY + BTO + 2x COE | C5: 1.25 | D5: =$G$4*C5 | E5: =D5*Assumptions!$B$4
A6: Mar | B6: Tax Season + Condos + 2x COE | C6: 1.15 | D6: =$G$4*C6 | E6: =D6*Assumptions!$B$4
A7: Apr | B7: Tax Deadline + Condos + 2x COE | C7: 1.05 | D7: =$G$4*C7 | E7: =D7*Assumptions!$B$4
A8: May | B8: BTO + 2x COE | C8: 1.05 | D8: =$G$4*C8 | E8: =D8*Assumptions!$B$4
A9: Jun | B9: Mid-Year + 2x COE | C9: 0.85 | D9: =$G$4*C9 | E9: =D9*Assumptions!$B$4
A10: Jul | B10: School Hols + 2x COE | C10: 0.75 | D10: =$G$4*C10 | E10: =D10*Assumptions!$B$4
A11: Aug | B11: BTO + 2x COE | C11: 1.05 | D11: =$G$4*C11 | E11: =D11*Assumptions!$B$4
A12: Sep | B12: Condos + 2x COE | C12: 0.85 | D12: =$G$4*C12 | E12: =D12*Assumptions!$B$4
A13: Oct | B13: Condos + 2x COE | C13: 0.85 | D13: =$G$4*C13 | E13: =D13*Assumptions!$B$4
A14: Nov | B14: BTO + Bonus + 2x COE | C14: 1.15 | D14: =$G$4*C14 | E14: =D14*Assumptions!$B$4
A15: Dec | B15: Year-End + Bonus + 2x COE | C15: 1.15 | D15: =$G$4*C15 | E15: =D15*Assumptions!$B$4
A16: TOTAL | D16: =SUM(D4:D15) | E16: =SUM(E4:E15)

Sheet Scenarios
A1: SCENARIO ANALYSIS (YEAR 5 MATURE)
A3: Scenario | B3: Market Capture | C3: Subscriber % | D3: Day Passes | E3: Subscribers | F3: Revenue | G3: Costs | H3: Profit
A4: Conservative | B4: 0.5 | C4: 0.03 | D4: =Assumptions!$D$45*B4 | E4: ='Yearly Projection'!$F$5*C4 | F4: =(D4*Assumptions!$B$4)+(E4*0.3*Assumptions!$B$5*12)+(E4*0.7*Assumptions!$B$6) | G4: =(D4*Assumptions!$B$12*Assumptions!$B$11)+(E4*Assumptions!$B$13*12*Assumptions!$B$11)+10000+(F4*Assumptions!$B$16) | H4: =F4-G4
A5: Base Case | B5: 1 | C5: 0.05 | D5: =Assumptions!$D$45*B5 | E5: ='Yearly Projection'!$F$5*C5 | F5: =(D5*Assumptions!$B$4)+(E5*0.3*Assumptions!$B$5*12)+(E5*0.7*Assumptions!$B$6) | G5: =(D5*Assumptions!$B$12*Assumptions!$B$11)+(E5*Assumptions!$B$13*12*Assumptions!$B$11)+15000+(F5*Assumptions!$B$16) | H5: =F5-G5
A6: Optimistic | B6: 1.5 | C6: 0.08 | D6: =Assumptions!$D$45*B6 | E6: ='Yearly Projection'!$F$5*C6 | F6: =(D6*Assumptions!$B$4)+(E6*0.3*Assumptions!$B$5*12)+(E6*0.7*Assumptions!$B$6) | G6: =(D6*Assumptions!$B$12*Assumptions!$B$11)+(E6*Assumptions!$B$13*12*Assumptions!$B$11)+20000+(F6*Assumptions!$B$16) | H6: =F6-G6

Sheet Referral
A1: REFERRAL PROGRAM ECONOMICS
A3: Event | B3: Revenue | C3: Cost | D3: Net
A4: User B buys day pass | B4: =Assumptions!B4 | C4: =Assumptions!$B$11*Assumptions!$B$12 | D4: =B4-C4
A5: User A gets free day pass | B5: 0 | C5: =Assumptions!$B$11*Assumptions!$B$12 | D5: =B5-C5
A6: TOTAL PER REFERRAL | B6: =SUM(B4:B5) | C6: =SUM(C4:C5) | D6: =SUM(D4:D5)
A8: REFERRAL IMPACT PROJECTION
A10: Monthly Referrals | B10: Additional Revenue/Yr | C10: Additional Profit/Yr
A11: 100 | B11: =A11*$B$6*12 | C11: =A11*$D$6*12
A12: 500 | B12: =A12*$B$6*12 | C12: =A12*$D$6*12
A13: 1000 | B13: =A13*$B$6*12 | C13: =A13*$D$6*12
A14: 5000 | B14: =A14*$B$6*12 | C14: =A14*$D$6*12
A15: 10000 | B15: =A15*$B$6*12 | C15: =A15*$D$6*12
